ScuffedAPI/__init__.py
ScuffedAPI-0.0.4.dist-info/LICENSE
ScuffedAPI-0.0.4.dist-info/METADATA
ScuffedAPI-0.0.4.dist-info/WHEEL
ScuffedAPI-0.0.4.dist-info/top_level.txt
ScuffedAPI-0.0.4.dist-info/RECORD
