Metadata-Version: 2.1
Name: ScuffedAPI
Version: 0.0.4
Summary: Python wrapper for ScuffedAPI API.
Home-page: https://github.com/xMistt/ScuffedAPI-Wrapper
Author: Pirxcy
License: UNKNOWN
Platform: UNKNOWN
Classifier: Programming Language :: Python :: 3
Classifier: License :: OSI Approved :: MIT License
Classifier: Operating System :: OS Independent
Requires-Dist: requests
